toplot/__init__.py
toplot/algorithms.py
toplot/hidden.py
toplot/scattermap.py
toplot/weights.py
toplot-1.1.0.dist-info/METADATA
toplot-1.1.0.dist-info/WHEEL
toplot-1.1.0.dist-info/licenses/LICENSE
toplot-1.1.0.dist-info/RECORD
