Metadata-Version: 2.4
Name: toplot
Version: 1.1.0
Summary: Visualize the weights (i.e., topics) and hidden units (i.e., topic proportions) of topic models
Author-email: Hylke Donker <h.c.donker@umcg.nl>, Dorien Neijzen <d.neijzen@umcg.nl>
License-Expression: MIT
License-File: LICENSE
Keywords: topic models,visualization
Requires-Python: >=3.10
Requires-Dist: matplotlib
Requires-Dist: numpy
Requires-Dist: pandas
Requires-Dist: python-tsp
Requires-Dist: seaborn
